MANIFEST.in
README.md
VERSION
setup.py
ramses/__init__.py
ramses/acl.py
ramses/auth.py
ramses/generators.py
ramses/models.py
ramses/registry.py
ramses/utils.py
ramses/views.py
ramses.egg-info/PKG-INFO
ramses.egg-info/SOURCES.txt
ramses.egg-info/dependency_links.txt
ramses.egg-info/entry_points.txt
ramses.egg-info/not-zip-safe
ramses.egg-info/pbr.json
ramses.egg-info/requires.txt
ramses.egg-info/top_level.txt
ramses/scaffolds/__init__.py
ramses/scaffolds/__init__.pyc
ramses/scaffolds/__pycache__/__init__.cpython-33.pyc
ramses/scaffolds/__pycache__/__init__.cpython-34.pyc
ramses/scaffolds/__pycache__/__init__.cpython-35.pyc
ramses/scaffolds/ramses_starter/.gitignore_tmpl
ramses/scaffolds/ramses_starter/README.md
ramses/scaffolds/ramses_starter/api.raml_tmpl
ramses/scaffolds/ramses_starter/items.json
ramses/scaffolds/ramses_starter/local.ini_tmpl
ramses/scaffolds/ramses_starter/requirements.txt
ramses/scaffolds/ramses_starter/setup.py_tmpl
ramses/scaffolds/ramses_starter/+package+/__init__.py
ramses/scaffolds/ramses_starter/+package+/tests/__init__.py
ramses/scaffolds/ramses_starter/+package+/tests/api.raml
ramses/scaffolds/ramses_starter/+package+/tests/items.json
ramses/scaffolds/ramses_starter/+package+/tests/requirements.txt
ramses/scaffolds/ramses_starter/+package+/tests/test_api.py_tmpl
ramses/scripts/__init__.py
ramses/scripts/scaffold_test.py
tests/__init__.py
tests/fixtures.py
tests/test_acl.py
tests/test_auth.py
tests/test_generators.py
tests/test_models.py
tests/test_registry.py
tests/test_utils.py
tests/test_views.py