Metadata-Version: 1.1
Name: ramses
Version: 0.5.2
Summary: Generate a RESTful API for Pyramid using RAML
Home-page: https://github.com/ramses-tech/ramses
Author: Brandicted
Author-email: hello@ramses.tech
License: UNKNOWN
Keywords: web pyramid pylons ramses raml
Platform: UNKNOWN
Classifier: Programming Language :: Python
Classifier: Programming Language :: Python :: 2
Classifier: Programming Language :: Python :: 2.7
Classifier: Programming Language :: Python :: 3
Classifier: Programming Language :: Python :: 3.4
Classifier: Programming Language :: Python :: 3.5
Classifier: Framework :: Pyramid
Classifier: Topic :: Internet :: WWW/HTTP
Classifier: Topic :: Internet :: WWW/HTTP :: WSGI :: Application
